FeiJianduTezhengXuexiYuShenduXuexiZhongwenJiaochengUfldl/README.md
FeiJianduTezhengXuexiYuShenduXuexiZhongwenJiaochengUfldl/__init__.py
FeiJianduTezhengXuexiYuShenduXuexiZhongwenJiaochengUfldl/__main__.py
FeiJianduTezhengXuexiYuShenduXuexiZhongwenJiaochengUfldl/file.pdf
FeiJianduTezhengXuexiYuShenduXuexiZhongwenJiaochengUfldl/index.html
fei_jiandu_tezheng_xuexi_yu_shendu_xuexi_zhongwen_jiaocheng_ufldl-2024.3.2.0.dist-info/METADATA
fei_jiandu_tezheng_xuexi_yu_shendu_xuexi_zhongwen_jiaocheng_ufldl-2024.3.2.0.dist-info/WHEEL
fei_jiandu_tezheng_xuexi_yu_shendu_xuexi_zhongwen_jiaocheng_ufldl-2024.3.2.0.dist-info/entry_points.txt
fei_jiandu_tezheng_xuexi_yu_shendu_xuexi_zhongwen_jiaocheng_ufldl-2024.3.2.0.dist-info/top_level.txt
fei_jiandu_tezheng_xuexi_yu_shendu_xuexi_zhongwen_jiaocheng_ufldl-2024.3.2.0.dist-info/RECORD
